pbcpg_pipeline/__init__.py
pbcpg_pipeline/align_bam.py
pbcpg_pipeline/aligned_bam_to_cpg_scores.py
pbcpg_pipeline/download.py
pbcpg_pipeline/env.py
pbcpg_pipeline/export_bedgraph.py
pbcpg_pipeline/gene_body_methylation.py
pbcpg_pipeline/intersect.py
pbcpg_pipeline/mean.py
pbcpg_pipeline/merge.py
pbcpg_pipeline/methylation_hist.py
pbcpg_pipeline/parse_gff.py
pbcpg_pipeline/pbcpg_pipeline.py
pbcpg_pipeline/plot.py
pbcpg_pipeline/plot_bedtools.py
pbcpg_pipeline/plot_genes.py
pbcpg_pipeline/plot_repeats.py
pbcpg_pipeline/promoter_methylation.py
pbcpg_pipeline/version.py
pbcpg_pipeline/pileup_calling_model/info.txt
pbcpg_pipeline/pileup_calling_model/keras_metadata.pb
pbcpg_pipeline/pileup_calling_model/saved_model.pb
pbcpg_pipeline/pileup_calling_model/variables/variables.data-00000-of-00001
pbcpg_pipeline/pileup_calling_model/variables/variables.index
pbcpg_pipeline-0.2.4.dist-info/LICENSE
pbcpg_pipeline-0.2.4.dist-info/METADATA
pbcpg_pipeline-0.2.4.dist-info/WHEEL
pbcpg_pipeline-0.2.4.dist-info/entry_points.txt
pbcpg_pipeline-0.2.4.dist-info/top_level.txt
pbcpg_pipeline-0.2.4.dist-info/RECORD
