Metadata-Version: 2.1
Name: pbcpg-pipeline
Version: 0.2.4
Summary: Postprocess PacBio DNA methylation calls
Author-email: Anthony Aylward <aaylward@salk.edu>
Project-URL: Homepage, https://gitlab.com/salk-tm/pbcpg-pipeline
Project-URL: Documentation, https://salk-tm.gitlab.io/pbcpg-pipeline
Classifier: Programming Language :: Python :: 3
Classifier: Operating System :: OS Independent
Classifier: License :: OSI Approved :: MIT License
Requires-Python: <3.10,>=3.9
License-File: LICENSE
Requires-Dist: tensorflow (>=2.7)
Requires-Dist: numpy (==1.20.0)
Requires-Dist: biopython
Requires-Dist: pandas
Requires-Dist: pysam
Requires-Dist: tqdm
Requires-Dist: pybigwig
Requires-Dist: urllib3
Requires-Dist: pybedtools
Requires-Dist: gff2bed
Requires-Dist: seaborn
Requires-Dist: pyfaidx
